README.rst
setup.py
datatap/__init__.py
datatap/encoders.py
datatap/loading.py
datatap/datataps/__init__.py
datatap/datataps/base.py
datatap/datataps/memory.py
datatap/datataps/model.py
datatap/datataps/resource.py
datatap/datataps/s3bucket.py
datatap/datataps/streams.py
datatap/datataps/tarfile.py
datatap/datataps/zip.py
datatap/management/__init__.py
datatap/management/commands/__init__.py
datatap/management/commands/datatap.py
datatap/tests/__init__.py
datatap/tests/commands_tests.py
datatap/tests/integration_tests.py
datatap/tests/datataps/__init__.py
datatap/tests/datataps/jsonstream_tests.py
datatap/tests/datataps/memory_tests.py
datatap/tests/datataps/model_tests.py
datatap/tests/datataps/tarfile_tests.py
datatap/tests/datataps/zipfile_tests.py
django_datatap.egg-info/PKG-INFO
django_datatap.egg-info/SOURCES.txt
django_datatap.egg-info/dependency_links.txt
django_datatap.egg-info/top_level.txt