Metadata-Version: 1.1
Name: django-datatap
Version: 0.0.1
Summary: django-datatap is a fixture system enabling applications to define their own loading and dumping process while supporting file asset storage.
Home-page: http://github.com/zbyte64/django-datatap
Author: Jason Kraus
Author-email: zbyte64@gmail.com
License: New BSD License
Keywords: django fixtures datatap
Platform: UNKNOWN
Classifier: Programming Language :: Python
Classifier: Operating System :: OS Independent
Classifier: Natural Language :: English
Classifier: Development Status :: 3 - Alpha
Classifier: Intended Audience :: Developers
Classifier: Topic :: Internet :: WWW/HTTP :: Dynamic Content
